{
  "docusaurus-plugin-content-docs": {
    "default": {
      "loadedVersions": [
        {
          "versionName": "current",
          "label": "Next",
          "banner": null,
          "badge": false,
          "noIndex": false,
          "className": "docs-version-current",
          "path": "/docs",
          "tagsPath": "/docs/tags",
          "editUrl": "https://github.com/facebook/docusaurus/tree/main/packages/create-docusaurus/templates/shared/docs",
          "editUrlLocalized": "https://github.com/facebook/docusaurus/tree/main/packages/create-docusaurus/templates/shared/i18n/en/docusaurus-plugin-content-docs/current",
          "isLast": true,
          "routePriority": -1,
          "sidebarFilePath": "/workspace/fakela.github.io/sidebars.js",
          "contentPath": "/workspace/fakela.github.io/docs",
          "contentPathLocalized": "/workspace/fakela.github.io/i18n/en/docusaurus-plugin-content-docs/current",
          "docs": [
            {
              "unversionedId": "intro",
              "id": "intro",
              "title": "Favour Kelvin",
              "description": "I’m a technical writer with experience in creating documentation for external customers and internal engineering teams. I’ve managed large, established documentation libraries and created original documentation for new systems and services. My writing philosophy is to treat documentation like code. This means writing with open-source systems that accommodate community input and help reduce the documentation burden on developers.",
              "source": "@site/docs/intro.md",
              "sourceDirName": ".",
              "slug": "/intro",
              "permalink": "/docs/intro",
              "draft": false,
              "editUrl": "https://github.com/facebook/docusaurus/tree/main/packages/create-docusaurus/templates/shared/docs/intro.md",
              "tags": [],
              "version": "current",
              "sidebarPosition": 1,
              "frontMatter": {
                "sidebar_position": 1,
                "sidebar_label": "Work Experience"
              },
              "sidebar": "tutorialSidebar",
              "next": {
                "title": "Writing Samples",
                "permalink": "/docs/category/writing-samples"
              }
            },
            {
              "unversionedId": "tutorial-basics/api",
              "id": "tutorial-basics/api",
              "title": "API Documentation",
              "description": "Welcome to the API Documentation section of my portfolio! As a dedicated technical writer, I excel in creating clear, detailed, and user-friendly API documentation that facilitates seamless integration and interaction with software systems. Below, you'll find a sample of my work in this realm:",
              "source": "@site/docs/tutorial-basics/api.md",
              "sourceDirName": "tutorial-basics",
              "slug": "/tutorial-basics/api",
              "permalink": "/docs/tutorial-basics/api",
              "draft": false,
              "editUrl": "https://github.com/facebook/docusaurus/tree/main/packages/create-docusaurus/templates/shared/docs/tutorial-basics/api.md",
              "tags": [],
              "version": "current",
              "sidebarPosition": 6,
              "frontMatter": {
                "sidebar_position": 6,
                "sidebar_label": "API Documentation"
              },
              "sidebar": "tutorialSidebar",
              "previous": {
                "title": "Markdown Features",
                "permalink": "/docs/tutorial-basics/markdown-features"
              },
              "next": {
                "title": "How-to Guides",
                "permalink": "/docs/tutorial-basics/how-to-guide"
              }
            },
            {
              "unversionedId": "tutorial-basics/blogs",
              "id": "tutorial-basics/blogs",
              "title": "blogs",
              "description": "",
              "source": "@site/docs/tutorial-basics/blogs.md",
              "sourceDirName": "tutorial-basics",
              "slug": "/tutorial-basics/blogs",
              "permalink": "/docs/tutorial-basics/blogs",
              "draft": false,
              "editUrl": "https://github.com/facebook/docusaurus/tree/main/packages/create-docusaurus/templates/shared/docs/tutorial-basics/blogs.md",
              "tags": [],
              "version": "current",
              "sidebarPosition": 1,
              "frontMatter": {
                "sidebar_position": 1,
                "sidebar_label": "Blogs and Articles"
              },
              "sidebar": "tutorialSidebar",
              "previous": {
                "title": "Writing Samples",
                "permalink": "/docs/category/writing-samples"
              },
              "next": {
                "title": "FAQs",
                "permalink": "/docs/tutorial-basics/faqs"
              }
            },
            {
              "unversionedId": "tutorial-basics/faqs",
              "id": "tutorial-basics/faqs",
              "title": "faqs",
              "description": "",
              "source": "@site/docs/tutorial-basics/faqs.md",
              "sourceDirName": "tutorial-basics",
              "slug": "/tutorial-basics/faqs",
              "permalink": "/docs/tutorial-basics/faqs",
              "draft": false,
              "editUrl": "https://github.com/facebook/docusaurus/tree/main/packages/create-docusaurus/templates/shared/docs/tutorial-basics/faqs.md",
              "tags": [],
              "version": "current",
              "sidebarPosition": 1,
              "frontMatter": {
                "sidebar_position": 1,
                "sidebar_label": "FAQs"
              },
              "sidebar": "tutorialSidebar",
              "previous": {
                "title": "Blogs and Articles",
                "permalink": "/docs/tutorial-basics/blogs"
              },
              "next": {
                "title": "Glossaries and Terminology Lists",
                "permalink": "/docs/tutorial-basics/glossary"
              }
            },
            {
              "unversionedId": "tutorial-basics/glossary",
              "id": "tutorial-basics/glossary",
              "title": "glossary",
              "description": "",
              "source": "@site/docs/tutorial-basics/glossary.md",
              "sourceDirName": "tutorial-basics",
              "slug": "/tutorial-basics/glossary",
              "permalink": "/docs/tutorial-basics/glossary",
              "draft": false,
              "editUrl": "https://github.com/facebook/docusaurus/tree/main/packages/create-docusaurus/templates/shared/docs/tutorial-basics/glossary.md",
              "tags": [],
              "version": "current",
              "sidebarPosition": 1,
              "frontMatter": {
                "sidebar_position": 1,
                "sidebar_label": "Glossaries and Terminology Lists"
              },
              "sidebar": "tutorialSidebar",
              "previous": {
                "title": "FAQs",
                "permalink": "/docs/tutorial-basics/faqs"
              },
              "next": {
                "title": "Internal Documentation",
                "permalink": "/docs/tutorial-basics/internal-docs"
              }
            },
            {
              "unversionedId": "tutorial-basics/how-to-guide",
              "id": "tutorial-basics/how-to-guide",
              "title": "How-to Guide Documentation Sample",
              "description": "Welcome to my How-to Guide Documentation portfolio section! As a technical writer, I specialize in creating clear and concise step-by-step guides that assist users in performing specific tasks. Below is an example of my work in this category:",
              "source": "@site/docs/tutorial-basics/how-to-guide.md",
              "sourceDirName": "tutorial-basics",
              "slug": "/tutorial-basics/how-to-guide",
              "permalink": "/docs/tutorial-basics/how-to-guide",
              "draft": false,
              "editUrl": "https://github.com/facebook/docusaurus/tree/main/packages/create-docusaurus/templates/shared/docs/tutorial-basics/how-to-guide.md",
              "tags": [],
              "version": "current",
              "sidebarPosition": 7,
              "frontMatter": {
                "sidebar_position": 7,
                "sidebar_label": "How-to Guides"
              },
              "sidebar": "tutorialSidebar",
              "previous": {
                "title": "API Documentation",
                "permalink": "/docs/tutorial-basics/api"
              },
              "next": {
                "title": "Tutorials Documentation",
                "permalink": "/docs/tutorial-basics/tutorial"
              }
            },
            {
              "unversionedId": "tutorial-basics/internal-docs",
              "id": "tutorial-basics/internal-docs",
              "title": "internal-docs",
              "description": "",
              "source": "@site/docs/tutorial-basics/internal-docs.md",
              "sourceDirName": "tutorial-basics",
              "slug": "/tutorial-basics/internal-docs",
              "permalink": "/docs/tutorial-basics/internal-docs",
              "draft": false,
              "editUrl": "https://github.com/facebook/docusaurus/tree/main/packages/create-docusaurus/templates/shared/docs/tutorial-basics/internal-docs.md",
              "tags": [],
              "version": "current",
              "sidebarPosition": 1,
              "frontMatter": {
                "sidebar_position": 1,
                "sidebar_label": "Internal Documentation"
              },
              "sidebar": "tutorialSidebar",
              "previous": {
                "title": "Glossaries and Terminology Lists",
                "permalink": "/docs/tutorial-basics/glossary"
              },
              "next": {
                "title": "Newsletter Contributions",
                "permalink": "/docs/tutorial-basics/newsletter"
              }
            },
            {
              "unversionedId": "tutorial-basics/markdown-features",
              "id": "tutorial-basics/markdown-features",
              "title": "Markdown Features",
              "description": "Docusaurus supports Markdown and a few additional features.",
              "source": "@site/docs/tutorial-basics/markdown-features.mdx",
              "sourceDirName": "tutorial-basics",
              "slug": "/tutorial-basics/markdown-features",
              "permalink": "/docs/tutorial-basics/markdown-features",
              "draft": false,
              "editUrl": "https://github.com/facebook/docusaurus/tree/main/packages/create-docusaurus/templates/shared/docs/tutorial-basics/markdown-features.mdx",
              "tags": [],
              "version": "current",
              "sidebarPosition": 4,
              "frontMatter": {
                "sidebar_position": 4
              },
              "sidebar": "tutorialSidebar",
              "previous": {
                "title": "User Manuals and Guides",
                "permalink": "/docs/tutorial-basics/user-manual"
              },
              "next": {
                "title": "API Documentation",
                "permalink": "/docs/tutorial-basics/api"
              }
            },
            {
              "unversionedId": "tutorial-basics/newsletter",
              "id": "tutorial-basics/newsletter",
              "title": "newsletter",
              "description": "",
              "source": "@site/docs/tutorial-basics/newsletter.md",
              "sourceDirName": "tutorial-basics",
              "slug": "/tutorial-basics/newsletter",
              "permalink": "/docs/tutorial-basics/newsletter",
              "draft": false,
              "editUrl": "https://github.com/facebook/docusaurus/tree/main/packages/create-docusaurus/templates/shared/docs/tutorial-basics/newsletter.md",
              "tags": [],
              "version": "current",
              "sidebarPosition": 1,
              "frontMatter": {
                "sidebar_position": 1,
                "sidebar_label": "Newsletter Contributions"
              },
              "sidebar": "tutorialSidebar",
              "previous": {
                "title": "Internal Documentation",
                "permalink": "/docs/tutorial-basics/internal-docs"
              },
              "next": {
                "title": "Release Notes",
                "permalink": "/docs/tutorial-basics/release-notes"
              }
            },
            {
              "unversionedId": "tutorial-basics/release-notes",
              "id": "tutorial-basics/release-notes",
              "title": "release-notes",
              "description": "",
              "source": "@site/docs/tutorial-basics/release-notes.md",
              "sourceDirName": "tutorial-basics",
              "slug": "/tutorial-basics/release-notes",
              "permalink": "/docs/tutorial-basics/release-notes",
              "draft": false,
              "editUrl": "https://github.com/facebook/docusaurus/tree/main/packages/create-docusaurus/templates/shared/docs/tutorial-basics/release-notes.md",
              "tags": [],
              "version": "current",
              "sidebarPosition": 1,
              "frontMatter": {
                "sidebar_position": 1,
                "sidebar_label": "Release Notes"
              },
              "sidebar": "tutorialSidebar",
              "previous": {
                "title": "Newsletter Contributions",
                "permalink": "/docs/tutorial-basics/newsletter"
              },
              "next": {
                "title": "Style Guides",
                "permalink": "/docs/tutorial-basics/style-guide"
              }
            },
            {
              "unversionedId": "tutorial-basics/style-guide",
              "id": "tutorial-basics/style-guide",
              "title": "style-guide",
              "description": "",
              "source": "@site/docs/tutorial-basics/style-guide.md",
              "sourceDirName": "tutorial-basics",
              "slug": "/tutorial-basics/style-guide",
              "permalink": "/docs/tutorial-basics/style-guide",
              "draft": false,
              "editUrl": "https://github.com/facebook/docusaurus/tree/main/packages/create-docusaurus/templates/shared/docs/tutorial-basics/style-guide.md",
              "tags": [],
              "version": "current",
              "sidebarPosition": 1,
              "frontMatter": {
                "sidebar_position": 1,
                "sidebar_label": "Style Guides"
              },
              "sidebar": "tutorialSidebar",
              "previous": {
                "title": "Release Notes",
                "permalink": "/docs/tutorial-basics/release-notes"
              },
              "next": {
                "title": "Troubleshooting Guides",
                "permalink": "/docs/tutorial-basics/troubleshooting"
              }
            },
            {
              "unversionedId": "tutorial-basics/troubleshooting",
              "id": "tutorial-basics/troubleshooting",
              "title": "troubleshooting",
              "description": "",
              "source": "@site/docs/tutorial-basics/troubleshooting.md",
              "sourceDirName": "tutorial-basics",
              "slug": "/tutorial-basics/troubleshooting",
              "permalink": "/docs/tutorial-basics/troubleshooting",
              "draft": false,
              "editUrl": "https://github.com/facebook/docusaurus/tree/main/packages/create-docusaurus/templates/shared/docs/tutorial-basics/troubleshooting.md",
              "tags": [],
              "version": "current",
              "sidebarPosition": 1,
              "frontMatter": {
                "sidebar_position": 1,
                "sidebar_label": "Troubleshooting Guides"
              },
              "sidebar": "tutorialSidebar",
              "previous": {
                "title": "Style Guides",
                "permalink": "/docs/tutorial-basics/style-guide"
              },
              "next": {
                "title": "User Manuals and Guides",
                "permalink": "/docs/tutorial-basics/user-manual"
              }
            },
            {
              "unversionedId": "tutorial-basics/tutorial",
              "id": "tutorial-basics/tutorial",
              "title": "Tutorials Documentation Sample",
              "description": "Welcome to my Tutorials Documentation portfolio section! As a technical writer, I specialize in creating comprehensive and easy-to-follow tutorials that guide users through complex processes step by step. Below, you'll find an example of my work in this domain:",
              "source": "@site/docs/tutorial-basics/tutorial.md",
              "sourceDirName": "tutorial-basics",
              "slug": "/tutorial-basics/tutorial",
              "permalink": "/docs/tutorial-basics/tutorial",
              "draft": false,
              "editUrl": "https://github.com/facebook/docusaurus/tree/main/packages/create-docusaurus/templates/shared/docs/tutorial-basics/tutorial.md",
              "tags": [],
              "version": "current",
              "sidebarPosition": 7,
              "frontMatter": {
                "sidebar_position": 7,
                "sidebar_label": "Tutorials Documentation"
              },
              "sidebar": "tutorialSidebar",
              "previous": {
                "title": "How-to Guides",
                "permalink": "/docs/tutorial-basics/how-to-guide"
              },
              "next": {
                "title": "Tutorial - Extras",
                "permalink": "/docs/category/tutorial---extras"
              }
            },
            {
              "unversionedId": "tutorial-basics/user-manual",
              "id": "tutorial-basics/user-manual",
              "title": "User Manuals and Guides",
              "description": "Welcome to my User Manuals and Guides portfolio section! As a technical writer, I specialize in crafting clear and comprehensive user documentation that helps users navigate and utilize products effectively. Below are some examples of my work in this domain:",
              "source": "@site/docs/tutorial-basics/user-manual.md",
              "sourceDirName": "tutorial-basics",
              "slug": "/tutorial-basics/user-manual",
              "permalink": "/docs/tutorial-basics/user-manual",
              "draft": false,
              "editUrl": "https://github.com/facebook/docusaurus/tree/main/packages/create-docusaurus/templates/shared/docs/tutorial-basics/user-manual.md",
              "tags": [],
              "version": "current",
              "sidebarPosition": 1,
              "frontMatter": {
                "sidebar_position": 1,
                "sidebar_label": "User Manuals and Guides"
              },
              "sidebar": "tutorialSidebar",
              "previous": {
                "title": "Troubleshooting Guides",
                "permalink": "/docs/tutorial-basics/troubleshooting"
              },
              "next": {
                "title": "Markdown Features",
                "permalink": "/docs/tutorial-basics/markdown-features"
              }
            },
            {
              "unversionedId": "tutorial-extras/manage-docs-versions",
              "id": "tutorial-extras/manage-docs-versions",
              "title": "Manage Docs Versions",
              "description": "Docusaurus can manage multiple versions of your docs.",
              "source": "@site/docs/tutorial-extras/manage-docs-versions.md",
              "sourceDirName": "tutorial-extras",
              "slug": "/tutorial-extras/manage-docs-versions",
              "permalink": "/docs/tutorial-extras/manage-docs-versions",
              "draft": false,
              "editUrl": "https://github.com/facebook/docusaurus/tree/main/packages/create-docusaurus/templates/shared/docs/tutorial-extras/manage-docs-versions.md",
              "tags": [],
              "version": "current",
              "sidebarPosition": 1,
              "frontMatter": {
                "sidebar_position": 1
              },
              "sidebar": "tutorialSidebar",
              "previous": {
                "title": "Tutorial - Extras",
                "permalink": "/docs/category/tutorial---extras"
              },
              "next": {
                "title": "Translate your site",
                "permalink": "/docs/tutorial-extras/translate-your-site"
              }
            },
            {
              "unversionedId": "tutorial-extras/translate-your-site",
              "id": "tutorial-extras/translate-your-site",
              "title": "Translate your site",
              "description": "Let's translate docs/intro.md to French.",
              "source": "@site/docs/tutorial-extras/translate-your-site.md",
              "sourceDirName": "tutorial-extras",
              "slug": "/tutorial-extras/translate-your-site",
              "permalink": "/docs/tutorial-extras/translate-your-site",
              "draft": false,
              "editUrl": "https://github.com/facebook/docusaurus/tree/main/packages/create-docusaurus/templates/shared/docs/tutorial-extras/translate-your-site.md",
              "tags": [],
              "version": "current",
              "sidebarPosition": 2,
              "frontMatter": {
                "sidebar_position": 2
              },
              "sidebar": "tutorialSidebar",
              "previous": {
                "title": "Manage Docs Versions",
                "permalink": "/docs/tutorial-extras/manage-docs-versions"
              }
            }
          ],
          "drafts": [],
          "sidebars": {
            "tutorialSidebar": [
              {
                "type": "doc",
                "id": "intro",
                "label": "Work Experience"
              },
              {
                "type": "category",
                "label": "Writing Samples",
                "collapsible": true,
                "collapsed": true,
                "items": [
                  {
                    "type": "doc",
                    "id": "tutorial-basics/blogs",
                    "label": "Blogs and Articles"
                  },
                  {
                    "type": "doc",
                    "id": "tutorial-basics/faqs",
                    "label": "FAQs"
                  },
                  {
                    "type": "doc",
                    "id": "tutorial-basics/glossary",
                    "label": "Glossaries and Terminology Lists"
                  },
                  {
                    "type": "doc",
                    "id": "tutorial-basics/internal-docs",
                    "label": "Internal Documentation"
                  },
                  {
                    "type": "doc",
                    "id": "tutorial-basics/newsletter",
                    "label": "Newsletter Contributions"
                  },
                  {
                    "type": "doc",
                    "id": "tutorial-basics/release-notes",
                    "label": "Release Notes"
                  },
                  {
                    "type": "doc",
                    "id": "tutorial-basics/style-guide",
                    "label": "Style Guides"
                  },
                  {
                    "type": "doc",
                    "id": "tutorial-basics/troubleshooting",
                    "label": "Troubleshooting Guides"
                  },
                  {
                    "type": "doc",
                    "id": "tutorial-basics/user-manual",
                    "label": "User Manuals and Guides"
                  },
                  {
                    "type": "doc",
                    "id": "tutorial-basics/markdown-features"
                  },
                  {
                    "type": "doc",
                    "id": "tutorial-basics/api",
                    "label": "API Documentation"
                  },
                  {
                    "type": "doc",
                    "id": "tutorial-basics/how-to-guide",
                    "label": "How-to Guides"
                  },
                  {
                    "type": "doc",
                    "id": "tutorial-basics/tutorial",
                    "label": "Tutorials Documentation"
                  }
                ],
                "link": {
                  "type": "generated-index",
                  "description": "This section provides examples of my technical writing. I wrote this documentation for product knowledge base, internal engineering teams, and customer-facing, support teams, etc. The pages in each section are not the full documentation for a product or service.",
                  "slug": "/category/writing-samples",
                  "permalink": "/docs/category/writing-samples"
                }
              },
              {
                "type": "category",
                "label": "Tutorial - Extras",
                "collapsible": true,
                "collapsed": true,
                "items": [
                  {
                    "type": "doc",
                    "id": "tutorial-extras/manage-docs-versions"
                  },
                  {
                    "type": "doc",
                    "id": "tutorial-extras/translate-your-site"
                  }
                ],
                "link": {
                  "type": "generated-index",
                  "slug": "/category/tutorial---extras",
                  "permalink": "/docs/category/tutorial---extras"
                }
              }
            ]
          }
        }
      ]
    }
  },
  "docusaurus-plugin-content-blog": {
    "default": {
      "blogSidebarTitle": "Recent posts",
      "blogPosts": [
        {
          "id": "welcome",
          "metadata": {
            "permalink": "/blog/welcome",
            "editUrl": "https://github.com/facebook/docusaurus/tree/main/packages/create-docusaurus/templates/shared/blog/2021-08-26-welcome/index.md",
            "source": "@site/blog/2021-08-26-welcome/index.md",
            "title": "Welcome",
            "description": "Docusaurus blogging features are powered by the blog plugin.",
            "date": "2021-08-26T00:00:00.000Z",
            "formattedDate": "August 26, 2021",
            "tags": [
              {
                "label": "facebook",
                "permalink": "/blog/tags/facebook"
              },
              {
                "label": "hello",
                "permalink": "/blog/tags/hello"
              },
              {
                "label": "docusaurus",
                "permalink": "/blog/tags/docusaurus"
              }
            ],
            "readingTime": 0.405,
            "hasTruncateMarker": false,
            "authors": [
              {
                "name": "Sébastien Lorber",
                "title": "Docusaurus maintainer",
                "url": "https://sebastienlorber.com",
                "imageURL": "https://github.com/slorber.png",
                "key": "slorber"
              },
              {
                "name": "Yangshun Tay",
                "title": "Front End Engineer @ Facebook",
                "url": "https://github.com/yangshun",
                "imageURL": "https://github.com/yangshun.png",
                "key": "yangshun"
              }
            ],
            "frontMatter": {
              "slug": "welcome",
              "title": "Welcome",
              "authors": [
                "slorber",
                "yangshun"
              ],
              "tags": [
                "facebook",
                "hello",
                "docusaurus"
              ]
            },
            "nextItem": {
              "title": "MDX Blog Post",
              "permalink": "/blog/mdx-blog-post"
            }
          },
          "content": "[Docusaurus blogging features](https://docusaurus.io/docs/blog) are powered by the [blog plugin](https://docusaurus.io/docs/api/plugins/@docusaurus/plugin-content-blog).\n\nSimply add Markdown files (or folders) to the `blog` directory.\n\nRegular blog authors can be added to `authors.yml`.\n\nThe blog post date can be extracted from filenames, such as:\n\n- `2019-05-30-welcome.md`\n- `2019-05-30-welcome/index.md`\n\nA blog post folder can be convenient to co-locate blog post images:\n\n![Docusaurus Plushie](./docusaurus-plushie-banner.jpeg)\n\nThe blog supports tags as well!\n\n**And if you don't want a blog**: just delete this directory, and use `blog: false` in your Docusaurus config."
        },
        {
          "id": "mdx-blog-post",
          "metadata": {
            "permalink": "/blog/mdx-blog-post",
            "editUrl": "https://github.com/facebook/docusaurus/tree/main/packages/create-docusaurus/templates/shared/blog/2021-08-01-mdx-blog-post.mdx",
            "source": "@site/blog/2021-08-01-mdx-blog-post.mdx",
            "title": "MDX Blog Post",
            "description": "Blog posts support Docusaurus Markdown features, such as MDX.",
            "date": "2021-08-01T00:00:00.000Z",
            "formattedDate": "August 1, 2021",
            "tags": [
              {
                "label": "docusaurus",
                "permalink": "/blog/tags/docusaurus"
              }
            ],
            "readingTime": 0.175,
            "hasTruncateMarker": false,
            "authors": [
              {
                "name": "Sébastien Lorber",
                "title": "Docusaurus maintainer",
                "url": "https://sebastienlorber.com",
                "imageURL": "https://github.com/slorber.png",
                "key": "slorber"
              }
            ],
            "frontMatter": {
              "slug": "mdx-blog-post",
              "title": "MDX Blog Post",
              "authors": [
                "slorber"
              ],
              "tags": [
                "docusaurus"
              ]
            },
            "prevItem": {
              "title": "Welcome",
              "permalink": "/blog/welcome"
            },
            "nextItem": {
              "title": "Long Blog Post",
              "permalink": "/blog/long-blog-post"
            }
          },
          "content": "Blog posts support [Docusaurus Markdown features](https://docusaurus.io/docs/markdown-features), such as [MDX](https://mdxjs.com/).\n\n:::tip\n\nUse the power of React to create interactive blog posts.\n\n```js\n<button onClick={() => alert('button clicked!')}>Click me!</button>\n```\n\n<button onClick={() => alert('button clicked!')}>Click me!</button>\n\n:::"
        },
        {
          "id": "long-blog-post",
          "metadata": {
            "permalink": "/blog/long-blog-post",
            "editUrl": "https://github.com/facebook/docusaurus/tree/main/packages/create-docusaurus/templates/shared/blog/2019-05-29-long-blog-post.md",
            "source": "@site/blog/2019-05-29-long-blog-post.md",
            "title": "Long Blog Post",
            "description": "This is the summary of a very long blog post,",
            "date": "2019-05-29T00:00:00.000Z",
            "formattedDate": "May 29, 2019",
            "tags": [
              {
                "label": "hello",
                "permalink": "/blog/tags/hello"
              },
              {
                "label": "docusaurus",
                "permalink": "/blog/tags/docusaurus"
              }
            ],
            "readingTime": 2.05,
            "hasTruncateMarker": true,
            "authors": [
              {
                "name": "Endilie Yacop Sucipto",
                "title": "Maintainer of Docusaurus",
                "url": "https://github.com/endiliey",
                "imageURL": "https://github.com/endiliey.png",
                "key": "endi"
              }
            ],
            "frontMatter": {
              "slug": "long-blog-post",
              "title": "Long Blog Post",
              "authors": "endi",
              "tags": [
                "hello",
                "docusaurus"
              ]
            },
            "prevItem": {
              "title": "MDX Blog Post",
              "permalink": "/blog/mdx-blog-post"
            },
            "nextItem": {
              "title": "First Blog Post",
              "permalink": "/blog/first-blog-post"
            }
          },
          "content": "This is the summary of a very long blog post,\n\nUse a `<!--` `truncate` `-->` comment to limit blog post size in the list view.\n\n<!--truncate-->\n\nLorem ipsum dolor sit amet, consectetur adipiscing elit. Pellentesque elementum dignissim ultricies. Fusce rhoncus ipsum tempor eros aliquam consequat. Lorem ipsum dolor sit amet\n\nLorem ipsum dolor sit amet, consectetur adipiscing elit. Pellentesque elementum dignissim ultricies. Fusce rhoncus ipsum tempor eros aliquam consequat. Lorem ipsum dolor sit amet\n\nLorem ipsum dolor sit amet, consectetur adipiscing elit. Pellentesque elementum dignissim ultricies. Fusce rhoncus ipsum tempor eros aliquam consequat. Lorem ipsum dolor sit amet\n\nLorem ipsum dolor sit amet, consectetur adipiscing elit. Pellentesque elementum dignissim ultricies. Fusce rhoncus ipsum tempor eros aliquam consequat. Lorem ipsum dolor sit amet\n\nLorem ipsum dolor sit amet, consectetur adipiscing elit. Pellentesque elementum dignissim ultricies. Fusce rhoncus ipsum tempor eros aliquam consequat. Lorem ipsum dolor sit amet\n\nLorem ipsum dolor sit amet, consectetur adipiscing elit. Pellentesque elementum dignissim ultricies. Fusce rhoncus ipsum tempor eros aliquam consequat. Lorem ipsum dolor sit amet\n\nLorem ipsum dolor sit amet, consectetur adipiscing elit. Pellentesque elementum dignissim ultricies. Fusce rhoncus ipsum tempor eros aliquam consequat. Lorem ipsum dolor sit amet\n\nLorem ipsum dolor sit amet, consectetur adipiscing elit. Pellentesque elementum dignissim ultricies. Fusce rhoncus ipsum tempor eros aliquam consequat. Lorem ipsum dolor sit amet\n\nLorem ipsum dolor sit amet, consectetur adipiscing elit. Pellentesque elementum dignissim ultricies. Fusce rhoncus ipsum tempor eros aliquam consequat. Lorem ipsum dolor sit amet\n\nLorem ipsum dolor sit amet, consectetur adipiscing elit. Pellentesque elementum dignissim ultricies. Fusce rhoncus ipsum tempor eros aliquam consequat. Lorem ipsum dolor sit amet\n\nLorem ipsum dolor sit amet, consectetur adipiscing elit. Pellentesque elementum dignissim ultricies. Fusce rhoncus ipsum tempor eros aliquam consequat. Lorem ipsum dolor sit amet\n\nLorem ipsum dolor sit amet, consectetur adipiscing elit. Pellentesque elementum dignissim ultricies. Fusce rhoncus ipsum tempor eros aliquam consequat. Lorem ipsum dolor sit amet\n\nLorem ipsum dolor sit amet, consectetur adipiscing elit. Pellentesque elementum dignissim ultricies. Fusce rhoncus ipsum tempor eros aliquam consequat. Lorem ipsum dolor sit amet\n\nLorem ipsum dolor sit amet, consectetur adipiscing elit. Pellentesque elementum dignissim ultricies. Fusce rhoncus ipsum tempor eros aliquam consequat. Lorem ipsum dolor sit amet\n\nLorem ipsum dolor sit amet, consectetur adipiscing elit. Pellentesque elementum dignissim ultricies. Fusce rhoncus ipsum tempor eros aliquam consequat. Lorem ipsum dolor sit amet\n\nLorem ipsum dolor sit amet, consectetur adipiscing elit. Pellentesque elementum dignissim ultricies. Fusce rhoncus ipsum tempor eros aliquam consequat. Lorem ipsum dolor sit amet"
        },
        {
          "id": "first-blog-post",
          "metadata": {
            "permalink": "/blog/first-blog-post",
            "editUrl": "https://github.com/facebook/docusaurus/tree/main/packages/create-docusaurus/templates/shared/blog/2019-05-28-first-blog-post.md",
            "source": "@site/blog/2019-05-28-first-blog-post.md",
            "title": "First Blog Post",
            "description": "Lorem ipsum dolor sit amet, consectetur adipiscing elit. Pellentesque elementum dignissim ultricies. Fusce rhoncus ipsum tempor eros aliquam consequat. Lorem ipsum dolor sit amet",
            "date": "2019-05-28T00:00:00.000Z",
            "formattedDate": "May 28, 2019",
            "tags": [
              {
                "label": "hola",
                "permalink": "/blog/tags/hola"
              },
              {
                "label": "docusaurus",
                "permalink": "/blog/tags/docusaurus"
              }
            ],
            "readingTime": 0.12,
            "hasTruncateMarker": false,
            "authors": [
              {
                "name": "Gao Wei",
                "title": "Docusaurus Core Team",
                "url": "https://github.com/wgao19",
                "image_url": "https://github.com/wgao19.png",
                "imageURL": "https://github.com/wgao19.png"
              }
            ],
            "frontMatter": {
              "slug": "first-blog-post",
              "title": "First Blog Post",
              "authors": {
                "name": "Gao Wei",
                "title": "Docusaurus Core Team",
                "url": "https://github.com/wgao19",
                "image_url": "https://github.com/wgao19.png",
                "imageURL": "https://github.com/wgao19.png"
              },
              "tags": [
                "hola",
                "docusaurus"
              ]
            },
            "prevItem": {
              "title": "Long Blog Post",
              "permalink": "/blog/long-blog-post"
            }
          },
          "content": "Lorem ipsum dolor sit amet, consectetur adipiscing elit. Pellentesque elementum dignissim ultricies. Fusce rhoncus ipsum tempor eros aliquam consequat. Lorem ipsum dolor sit amet"
        }
      ],
      "blogListPaginated": [
        {
          "items": [
            "welcome",
            "mdx-blog-post",
            "long-blog-post",
            "first-blog-post"
          ],
          "metadata": {
            "permalink": "/blog",
            "page": 1,
            "postsPerPage": 10,
            "totalPages": 1,
            "totalCount": 4,
            "blogDescription": "Blog",
            "blogTitle": "Blog"
          }
        }
      ],
      "blogTags": {
        "/blog/tags/facebook": {
          "label": "facebook",
          "items": [
            "welcome"
          ],
          "permalink": "/blog/tags/facebook",
          "pages": [
            {
              "items": [
                "welcome"
              ],
              "metadata": {
                "permalink": "/blog/tags/facebook",
                "page": 1,
                "postsPerPage": 10,
                "totalPages": 1,
                "totalCount": 1,
                "blogDescription": "Blog",
                "blogTitle": "Blog"
              }
            }
          ]
        },
        "/blog/tags/hello": {
          "label": "hello",
          "items": [
            "welcome",
            "long-blog-post"
          ],
          "permalink": "/blog/tags/hello",
          "pages": [
            {
              "items": [
                "welcome",
                "long-blog-post"
              ],
              "metadata": {
                "permalink": "/blog/tags/hello",
                "page": 1,
                "postsPerPage": 10,
                "totalPages": 1,
                "totalCount": 2,
                "blogDescription": "Blog",
                "blogTitle": "Blog"
              }
            }
          ]
        },
        "/blog/tags/docusaurus": {
          "label": "docusaurus",
          "items": [
            "welcome",
            "mdx-blog-post",
            "long-blog-post",
            "first-blog-post"
          ],
          "permalink": "/blog/tags/docusaurus",
          "pages": [
            {
              "items": [
                "welcome",
                "mdx-blog-post",
                "long-blog-post",
                "first-blog-post"
              ],
              "metadata": {
                "permalink": "/blog/tags/docusaurus",
                "page": 1,
                "postsPerPage": 10,
                "totalPages": 1,
                "totalCount": 4,
                "blogDescription": "Blog",
                "blogTitle": "Blog"
              }
            }
          ]
        },
        "/blog/tags/hola": {
          "label": "hola",
          "items": [
            "first-blog-post"
          ],
          "permalink": "/blog/tags/hola",
          "pages": [
            {
              "items": [
                "first-blog-post"
              ],
              "metadata": {
                "permalink": "/blog/tags/hola",
                "page": 1,
                "postsPerPage": 10,
                "totalPages": 1,
                "totalCount": 1,
                "blogDescription": "Blog",
                "blogTitle": "Blog"
              }
            }
          ]
        }
      },
      "blogTagsListPath": "/blog/tags"
    }
  },
  "docusaurus-plugin-content-pages": {
    "default": [
      {
        "type": "jsx",
        "permalink": "/",
        "source": "@site/src/pages/index.js"
      },
      {
        "type": "mdx",
        "permalink": "/markdown-page",
        "source": "@site/src/pages/markdown-page.md",
        "title": "Markdown page example",
        "description": "You don't need React to write simple standalone pages.",
        "frontMatter": {
          "title": "Markdown page example"
        }
      }
    ]
  },
  "docusaurus-plugin-debug": {},
  "docusaurus-theme-classic": {},
  "docusaurus-bootstrap-plugin": {},
  "docusaurus-mdx-fallback-plugin": {}
}