{
  "unversionedId": "intro",
  "id": "intro",
  "title": "Favour Kelvin",
  "description": "I’m a technical writer with experience in creating documentation for external customers and internal engineering teams. I’ve managed large, established documentation libraries and created original documentation for new systems and services. My writing philosophy is to treat documentation like code. This means writing with open-source systems that accommodate community input and help reduce the documentation burden on developers.",
  "source": "@site/docs/intro.md",
  "sourceDirName": ".",
  "slug": "/intro",
  "permalink": "/docs/intro",
  "draft": false,
  "editUrl": "https://github.com/facebook/docusaurus/tree/main/packages/create-docusaurus/templates/shared/docs/intro.md",
  "tags": [],
  "version": "current",
  "sidebarPosition": 1,
  "frontMatter": {
    "sidebar_position": 1,
    "sidebar_label": "Work Experience"
  },
  "sidebar": "tutorialSidebar",
  "next": {
    "title": "Writing Samples",
    "permalink": "/docs/category/writing-samples"
  }
}